opensesame_gemini/__init__.py
opensesame_gemini/opensesame.py
OpenSesameGemini-0.2.0.dist-info/METADATA
OpenSesameGemini-0.2.0.dist-info/WHEEL
OpenSesameGemini-0.2.0.dist-info/top_level.txt
OpenSesameGemini-0.2.0.dist-info/RECORD
