Metadata-Version: 2.1
Name: OpenSesameGemini
Version: 0.2.0
Summary: A package to interface with OpenSesame for generative AI models.
Classifier: Programming Language :: Python :: 3
Classifier: License :: OSI Approved :: MIT License
Classifier: Operating System :: OS Independent
Requires-Python: >=3.6
Requires-Dist: google-generativeai
Requires-Dist: requests
